pyramid_jwt_policy/__init__.py
pyramid_jwt_policy/exception.py
pyramid_jwt_policy/policy.py
pyramid_jwt_policy-1.0.0.dist-info/METADATA
pyramid_jwt_policy-1.0.0.dist-info/RECORD
pyramid_jwt_policy-1.0.0.dist-info/WHEEL
pyramid_jwt_policy-1.0.0.dist-info/top_level.txt
pyramid_jwt_policy-1.0.0.dist-info/zip-safe
