Metadata-Version: 2.1
Name: pyramid-jwt-policy
Version: 1.0.0
Summary: JWT authentication policy for Pyramid
Home-page: https://github.com/OvalMoney/pyramid_jwt_policy
Author: Simone Basso
Author-email: sb@ovalmoney.com
License: BSD
Keywords: Pyramid JWT authentication security
Platform: UNKNOWN
Classifier: Intended Audience :: Developers
Classifier: License :: DFSG approved
Classifier: License :: OSI Approved :: BSD License
Classifier: Operating System :: OS Independent
Classifier: Programming Language :: Python :: 2
Classifier: Programming Language :: Python :: 2.7
Classifier: Programming Language :: Python :: 3
Classifier: Programming Language :: Python :: 3.4
Classifier: Programming Language :: Python :: 3.5
Classifier: Programming Language :: Python :: 3.6
Classifier: Topic :: Software Development :: Libraries :: Python Modules
Provides-Extra: tests
Requires-Dist: pyramid
Requires-Dist: PyJWT
Provides-Extra: tests
Requires-Dist: pytest; extra == 'tests'
Requires-Dist: WebTest; extra == 'tests'
